croninfo/__init__.py
croninfo/__main__.py
croninfo/cli.py
croninfo/crontab.py
croninfo/py.typed
croninfo-1.0.1.dist-info/LICENSE.md
croninfo-1.0.1.dist-info/METADATA
croninfo-1.0.1.dist-info/WHEEL
croninfo-1.0.1.dist-info/entry_points.txt
croninfo-1.0.1.dist-info/top_level.txt
croninfo-1.0.1.dist-info/RECORD
