Metadata-Version: 2.1
Name: croninfo
Version: 1.0.1
Summary: Elegant Cron Expression Output via the CLI
Home-page: https://github.com/paulmonk/croninfo
Author: Paul Monk
Author-email: pypi@paulmonk.org
License: MIT
Project-URL: Homepage, https://github.com/paulmonk/croninfo
Project-URL: Changes, https://github.com/paulmonk/croninfo/blob/main/CHANGELOG.md
Project-URL: Source, https://github.com/paulmonk/croninfo
Project-URL: Issue Tracker, https://github.com/paulmonk/croninfo/issues
Keywords: cron
Classifier: Development Status :: 5 - Production/Stable
Classifier: Intended Audience :: Developers
Classifier: License :: OSI Approved :: MIT License
Classifier: Natural Language :: English
Classifier: Operating System :: OS Independent
Classifier: Programming Language :: Python :: 3 :: Only
Classifier: Programming Language :: Python :: 3
Classifier: Programming Language :: Python :: 3.7
Classifier: Programming Language :: Python :: 3.8
Classifier: Programming Language :: Python :: 3.9
Classifier: Programming Language :: Python :: 3.10
Requires-Python: >=3.7
License-File: LICENSE.md
Requires-Dist: rich
Requires-Dist: typer
Requires-Dist: tzlocal
Requires-Dist: importlib-metadata ; python_version < "3.8"
